AUTHORS.rst
CHANGELOG.rst
LICENSE
MANIFEST.in
README.rst
setup.py
jmbo_facebook/__init__.py
jmbo_facebook/admin.py
jmbo_facebook/admin_urls.py
jmbo_facebook/admin_views.py
jmbo_facebook/models.py
jmbo_facebook.egg-info/PKG-INFO
jmbo_facebook.egg-info/SOURCES.txt
jmbo_facebook.egg-info/dependency_links.txt
jmbo_facebook.egg-info/not-zip-safe
jmbo_facebook.egg-info/requires.txt
jmbo_facebook.egg-info/top_level.txt
jmbo_facebook/fixtures/photosizes.json
jmbo_facebook/migrations/0001_initial.py
jmbo_facebook/migrations/__init__.py
jmbo_facebook/templates/admin/jmbo_facebook/change_list.html
jmbo_facebook/templates/basic/jmbo_facebook/inclusion_tags/page_detail.html
jmbo_facebook/templates/basic/jmbo_facebook/inclusion_tags/page_list_item_widget.html
jmbo_facebook/templates/basic/jmbo_facebook/inclusion_tags/update_list_item_thumbnail.html
jmbo_facebook/templatetags/__init__.py
jmbo_facebook/templatetags/__init__.pyc
jmbo_facebook/templatetags/jmbo_facebook_tags.py
jmbo_facebook/templatetags/jmbo_facebook_tags.pyc